[
    {
        "name": "BaseConvo_Exchanging Info",
        "trigger": "on_base_convo",
        "level_nid": "13",
        "condition": "base_convo == 'Exchanging Info'",
        "commands": [],
        "only_once": false,
        "priority": 20,
        "_source": [
            "b;Village",
            "m;Silent Ground",
            "uu;Ryuuji;Left;Kai;Right",
            "e;Kai;CloseEyes",
            "s;Kai;I see{tgm}...{tgm} Yup, just like in Foliaga alright.",
            "s;Ryuuji;Except Samegoro's got pirates and bandits under his belt too.|And he's been handing out a good amount of coin for all those prisoners.",
            "e;Kai;NormalBlink,Smile",
            "s;Kai;Glad to see you haven't fallen into that.",
            "e;Ryuuji;CloseEyes,Smile",
            "s;Ryuuji;Just what kinda guy do you take me for?|{c:e;Ryuuji;NormalBlink,Smile}I might plunder and kill like a regular ol' pirate now, but I've got standards.",
            "e;Kai;CloseEyes,Smile",
            "s;Kai;You haven't changed a bit.",
            "s;Ryuuji;Neither have you.|{c:e;Ryuuji;NormalBlink,NoSmile}And hey, one last thing about Samegoro's forces.",
            "e;Kai;NormalBlink,NoSmile",
            "s;Kai;Yeah?",
            "s;Ryuuji;Keep an eye out for a woman named Agrona. She's bad news.",
            "e;Kai;HalfCloseEyes",
            "s;Kai;Agrona{tgm}...{tgm} Yeah. I know.",
            "s;Ryuuji;Huh?",
            "e;Kai;CloseEyes",
            "s;Kai;She was appointed as one of Samegoro's shoguns over a year ago.|{c:e;Kai;NormalBlink}There was always something fishy about her.|I never could figure out what it was exactly. She was way too elusive.|{c:e;Kai;CloseEyes}With what we know, I feel like we're getting close to an answer.",
            "s;Ryuuji;We'll just keep our eyes and ears open, then.",
            "e;Kai;NormalBlink",
            "s;Kai;Yeah.|{c:e;Kai;Smile}Thanks, Kenji. I knew I could count on you.",
            "if;game.check_alive('Kai') == True",
            "  increment_support_points;Ryuuji;Kai;1",
            "  sound;Item",
            "  alert;Kai and Ryuuji grew closer!",
            "else",
            "  sound;Item",
            "  alert;Ryuuji gained 11 EXP!",
            "  give_exp;Ryuuji;11",
            "end",
            "gvar;KaiRyuujiCh13;True",
            "remove_base_convo;Exchanging Info",
            "b",
            "mf"
        ],
        "nid": "13 BaseConvo_Exchanging Info"
    }
]