[
    {
        "name": "Intro",
        "trigger": "level_start",
        "level_nid": "13",
        "condition": "True",
        "commands": [],
        "only_once": false,
        "priority": 20,
        "_source": [
            "music_clear",
            "m;A Hint of Things to Come",
            "overworld_cinematic;0",
            "set_overworld_position;Krista;12;no_animate",
            "reveal_overworld_node;13;immediate",
            "reveal_overworld_road;12;13;immediate",
            "center_cursor;12",
            "toggle_narration_mode;open",
            "omove;Krista;13;no_block",
            "s;;With the threat of the Wyrmfang Pirates now gone,|Krista and friends continue onwards towards Edoyama.|The party decides to make a pit stop at a small island just off the coast of Medeas.;StyleNid=overworld_narration",
            "toggle_narration_mode;close",
            "change_tilemap;Chapter 13;reload",
            "music_clear",
            "chapter_title;_Chapter Sound",
            "trigger_script;BanditTag",
            "lvar;_minimum_deployment;15",
            "lvar;houseDestroy;0",
            "lvar;YellowHouse;False",
            "add_base_convo;One Year Ago",
            "if;game.check_alive('Lucy') == True and u('Rembrandt').team == 'player' and game.check_alive('Rembrandt') == True",
            "  add_base_convo;Retirement",
            "end",
            "if;game.check_alive('Alex') == True and game.check_alive('Taylor') == True",
            "  add_base_convo;Tea Time",
            "end",
            "if;u('Ryuuji').team == 'player' and u('Taiga').team == 'player'",
            "  add_base_convo;Too Many Ears",
            "end",
            "if;u('Ryuuji').team == 'player'",
            "  add_base_convo;Exchanging Info",
            "end",
            "ginc;ChapterFlag",
            "change_class;ForrestCopy;{e:u('Forrest').klass};silent",
            "change_class;KaiCopy;{e:u('Kai').klass};silent",
            "remove_all_units",
            "b;Ship",
            "end_skip",
            "music_clear",
            "m;Girl of the Plains",
            "uu;Krista;Right;Forrest;MidLeft;Kai;FarLeft",
            "bop;Krista",
            "e;Krista;Smile",
            "s;Krista;Oh, there's an island over there!",
            "s;Kai;That should be Isle Aotani.|Home to a few villages nestled in its central mountains.",
            "s;Forrest;We should stop here to rest and restock on supplies.",
            "e;Kai;Smile",
            "s;Kai;Thankfully, its largest village, Aotani Village, is right on the coast.|It's the perfect pit stop for travellers like us who are just passing through.",
            "e;Krista;Smile",
            "s;Krista;Nice! We'll head straight there.",
            "bop;Krista",
            "s;Krista;Set sail that-a-way!",
            "rrr",
            "t;close",
            "b",
            "add_group;Citizens;starting;immediate;stack",
            "center_cursor;9,17",
            "t;open",
            "end_skip",
            "location_card;Aotani Village",
            "spawn_group;Player;south;Player;normal;stack",
            "move;c7;9,12;normal;stack",
            "flicker_cursor;c7",
            "t;close",
            "b;Village",
            "t;open",
            "uu;Krista;MidLeft;Forrest;FarLeft;OldMan1;OffscreenRight",
            "move_portrait;OldMan1;Right",
            "s;OldMan1;Welcome to Aotani Village, dear travelers.|What brings you here?",
            "s;Krista;Long story short, we've got business at the capital, and we needed a place to stop.",
            "s;OldMan1;I humbly thank you for choosing to stay in our fair village.|Please make yourselves at home.",
            "e;Krista;Smile",
            "s;Krista;Thanks a lot!",
            "s;Forrest;Before we do, sir, I do have one question.",
            "s;OldMan1;Yes?",
            "s;Forrest;Have you heard anything strange going on with the empror lately?",
            "s;OldMan1;Strange? Hm{tgm}...{tgm} It's small, but there is one thing.",
            "s;Forrest;Please go on, sir.",
            "s;OldMan1;As you may have observed,|Aotani Village is a common stop for those travelling between Medeas and Merinas.|Thus, our local militia has always been in top form keeping our borders safe.|However, starting around a year ago,|the emperor has ordered half of the militia to be drafted at the capital.",
            "e;Forrest;CloseEyes",
            "s;Forrest;That's concerning.|{c:e;Forrest;NormalBlink}You need protection for your borders|even if the neighboring country is on friendly terms with your own.|It's a matter of basic security.",
            "s;OldMan1;Precisely, young one.|I'm sure a leader such as Emperor Samegoro understands such a fundamental concept.|So him giving out this order is unusual.",
            "e;Krista;NoSmile",
            "s;Krista;And you said this started a year ago?",
            "s;OldMan1;Yes, exactly.",
            "e;Krista;CloseEyes",
            "s;Krista;Hmm{tgm}...|{c:e;Krista;NormalBlink,Smile}{tgm}Well, thanks for the info, sir. This was very helpful.",
            "s;OldMan1;I am happy to be of service.|With all this in mind, could I ask a favor from all of you?",
            "e;Krista;NoSmile",
            "s;Krista;Sure, what's up?",
            "s;OldMan1;With our militia low on numbers,|would you be able to look after our farmlands on the outskirts of town?|It would only be for today.|Things have been quiet recently,|but the area has been susceptible to pirate attacks in the past.|I can see that you are all capable fighters,|but I also understand if this will be inconvenient.",
            "e;Krista;Smile",
            "s;Krista;I don't see a problem with it.|We've dealt with bandits and pirates plenty of times, so no need to worry.|We'll be on the look out.",
            "s;OldMan1;I humbly thank you for your kindness,{br}young one.|If there is trouble, I'll be sure to send in what forces we do have for assistance.|Just know that it will take them time to come due to distance.|I'll also arrange things with the villagers|to see if we can properly accommodate you all during your stay.",
            "s;Krista;Thank you very much, sir. We really appreciate it.",
            "rrr",
            "uu;Krista;Right;Forrest;MidLeft;Kai;FarLeft",
            "e;Forrest;CloseEyes",
            "s;Forrest;Archbishop Azalea and Emperor Samegoro exhibiting strange behavior|for one whole year{tgm}...",
            "s;Krista;This can't be coincidence.",
            "s;Kai;And Prince Ervan's death was a year ago too, was it not?",
            "e;Forrest;NormalBlink",
            "s;Forrest;Kai! You can't just say--",
            "e;Krista;CloseEyes",
            "s;Krista;It's fine.|{c:e;Krista;NormalBlink}Kai has a point. It could be connected.",
            "e;Forrest;HalfCloseEyes",
            "s;Forrest;...;no_talk",
            "s;Krista;Either way, it's been a long day.|Let's discuss this once we get settled.",
            "e;Forrest;NormalBlink",
            "s;Forrest;Understood.",
            "rrr",
            "t;close",
            "b",
            "base;Village;Kagaribi no Oyado",
            "load_unit;Haruki;other;Attack",
            "if;game.current_mode.growths == 'Lucky'",
            "  autolevel_to;Haruki;13;lucky",
            "  autolevel_to;Daigo;15;lucky",
            "else",
            "  autolevel_to;Haruki;13;fixed",
            "  autolevel_to;Daigo;15;fixed",
            "end",
            "promote;Daigo;silent",
            "remove_group;Player;immediate",
            "t;open",
            "end_skip",
            "music_clear",
            "m;Raid",
            "center_cursor;17,17",
            "add;Daigo;17,17;;stack;east",
            "flicker_cursor;Daigo",
            "u;Daigo;Right",
            "s;Daigo;Quiet, peaceful, and not a soldier in sight.{c:e;Daigo;HalfCloseEyes,Smile} Just like usual. Perfect.|{c:e;Daigo;NormalBlink,Smile}Let's go, boys!|The emperor's gonna pay a pretty penny for every villager, so keep 'em alive!",
            "r;Daigo",
            "move;Daigo;16,17",
            "center_cursor;0,0",
            "spawn_group;EnemyNW;west;starting;normal;stack",
            "wait;200",
            "center_cursor;15,0",
            "spawn_group;EnemyNE;east;starting;normal;stack",
            "wait;200",
            "center_cursor;0,8",
            "spawn_group;EnemyW;west;starting;normal;stack",
            "wait;200",
            "center_cursor;17,7",
            "spawn_group;EnemyE;east;starting;normal;stack",
            "wait;200",
            "center_cursor;9,17",
            "spawn_group;EnemyS;south;starting;normal;stack",
            "wait;200",
            "center_cursor;c1",
            "flicker_cursor;c1",
            "u;Man1;Right",
            "s;Man1;Pirates! Everyone, get inside! Now!!",
            "r;Man1",
            "move_group;Citizens;Citizens;normal;stack",
            "remove_group;Citizens",
            "center_cursor;8,0",
            "spawn_group;Player;north;starting;normal;stack",
            "flicker_cursor;Krista",
            "u;Krista;Right;;CloseEyes",
            "s;Krista;Just happened to be a day when the village gets raided, huh?|{c:e;Krista;NormalBlink}Alright guys, you know the drill.|Protect the villagers and their homes!",
            "r;Krista",
            "end_skip",
            "center_cursor;HouseNW",
            "flicker_cursor;HouseNW",
            "t;close",
            "b;House",
            "t;open",
            "uu;Woman1;Right;Taichi;MidLeft;Haruki;FarLeft",
            "s;Taichi;Ma! What's going on out there?",
            "s;Woman1;Pirates are attacking the village!|Taichi, Haruki, we have to stay inside no matter what.",
            "s;Haruki;No way, I'm not gonna sit around and do nothing.|I'm going out there!",
            "s;Taichi;Haruki, no! It's too dangerous.",
            "s;Haruki;We can't just let those pirates do whatever they want.|I'm going and you can't stop me!",
            "move_portrait;Haruki;OffscreenRight",
            "mirror;Woman1",
            "move_portrait;Woman1;FarRight",
            "s;Woman1;Haruki! No!!",
            "move_portrait;Taichi;MidRight",
            "s;Taichi;Ma, no! Don't go out there too!",
            "move_portrait;Woman1;Right;no_block",
            "move_portrait;Taichi;Left",
            "mirror;Woman1",
            "s;Taichi;I'll stay here and protect you. I promise.",
            "e;Taichi;CloseEyes",
            "s;Taichi;Dang it, Haruki{tgm}...{tgm} Don't be stupid out there.;StyleNid=thought_bubble",
            "rrr",
            "t;close",
            "b",
            "t;open",
            "end_skip",
            "add;Haruki;HouseNW;immediate;stack;fade",
            "center_cursor;Haruki",
            "move;Haruki;6,4;normal;stack",
            "flicker_cursor;Haruki",
            "u;Haruki;Right",
            "s;Haruki;If Taichi's not gonna do anything, I will.",
            "bop;Haruki",
            "s;Haruki;Just try to get past me, you dumb pirates! I can take you all on!",
            "r;Haruki",
            "end_skip",
            "s;;In this chapter, visiting houses will <red>not</> keep enemy units from interacting with them.;StyleNid=hint;no_sound",
            "t;close",
            "remove_group;Player;immediate",
            "arrange_formation",
            "center_cursor;Krista",
            "add_talk;Krista;Haruki",
            "if;u('Ryuuji').team == 'player'",
            "  prep;true;Prepare to Charge;<green>Guide</>;True;AccessLibrary;Access the guide for tips and tricks.;gba;no_chap_disp",
            "else",
            "  prep;true;Prepare to Charge;Guide;True;AccessLibrary;Access the guide for tips and tricks.;gba;no_chap_disp",
            "end"
        ],
        "nid": "13 Intro"
    }
]