[
    {
        "name": "BaseConvo_Hand Holding",
        "trigger": "on_base_convo",
        "level_nid": "15",
        "condition": "base_convo == 'Hand Holding'",
        "commands": [],
        "only_once": false,
        "priority": 20,
        "_source": [
            "b;VillageGate",
            "m;Respite in Battle",
            "uu;Felicity;OffscreenRight;Krista;OffscreenRight",
            "move_portrait;Felicity;Left",
            "e;Felicity;CloseEyes",
            "s;Felicity;Phew, finally out of there.|{c:e;Felicity;HalfCloseEyes}Why did we have to stop in a large city like this?|Couldn't we have gone somewhere else?",
            "move_portrait;Krista;Right",
            "e;Krista;Smile",
            "s;Krista;Oh, Felicity! There you are.",
            "e;Felicity;NormalBlink",
            "bop;Felicity",
            "mirror;Felicity",
            "s;Felicity;Your Highness?",
            "s;Krista;I figured you'd be out here.|{c:e;Krista;NoSmile}Are you doing okay?",
            "e;Felicity;CloseEyes",
            "s;Felicity;I am quite fine, thank you.",
            "e;Krista;HalfCloseEyes",
            "s;Krista;Aw, don't give me that! You're trembling like a leaf.|{c:e;Krista;NormalBlink}The crowds are making you nervous, huh?",
            "e;Felicity;HalfCloseEyes",
            "s;Felicity;...;no_talk",
            "e;Krista;Smile",
            "s;Krista;I know you don't like being around a ton of people, but there's a festival going on!|It's supposed to be fun!",
            "e;Felicity;CloseEyes",
            "s;Felicity;Hm{tgm}...",
            "s;Krista;And you don't have to be alone either. We can check things out together!",
            "e;Felicity;NormalBlink",
            "s;Felicity;Are you sure it's alright? I wouldn't want to bring down the mood.",
            "e;Krista;CloseEyes,Smile",
            "s;Krista;If I wasn't okay with it, I wouldn't be offering.",
            "e;Krista;NormalBlink,Smile",
            "move_portrait;Krista;MidRight",
            "s;Krista;Here. We can even hold hands like we usually do.",
            "bop;Felicity",
            "s;Felicity;O-Oh! Er, alright.",
            "move_portrait;Felicity;MidLeft",
            "e;Felicity;Smile",
            "s;Felicity;Thank you, Your Highness.",
            "e;Krista;CloseEyes,Smile",
            "s;Krista;Don't sweat it.|{c:e;Krista;Smile}Anyway, let's go!",
            "if;game.check_alive('Felicity') == True",
            "  increment_support_points;Krista;Felicity;1",
            "  sound;Item",
            "  alert;Krista and Felicity grew closer!",
            "else",
            "  sound;Item",
            "  alert;Krista gained 21 EXP!",
            "  give_exp;Krista;21",
            "end",
            "remove_base_convo;Hand Holding",
            "b"
        ],
        "nid": "15 BaseConvo_Hand Holding"
    }
]