[
    {
        "name": "SupportEccoJoshua",
        "trigger": "on_support",
        "level_nid": "Global",
        "condition": "check_pair('Ecco', 'Joshua')",
        "commands": [],
        "only_once": false,
        "priority": 20,
        "_source": [
            "t;close",
            "if;support_rank_nid == 'C'",
            "b;CastleInterior",
            "t;open",
            "m;Girl of the Plains",
            "uu;Joshua;Left;Ecco;Right",
            "s;Ecco;Hey, you! Over here.",
            "s;Joshua;Oh, hey there. Your name's Ecco, right?",
            "e;Ecco;Smile",
            "s;Ecco;Sure is.|{c:e;Ecco;NoSmile}Now, here's the thing. I'm a mercenary.|Sometimes there just aren't any contracts around to take up and I need money.",
            "s;Joshua;Totally get it.|My old man was a mercenary, and I pick up a couple jobs here and there too.|That said, does it look like I'm made of money to you?|My parents always warned me about giving handouts.",
            "e;Ecco;HalfCloseEyes",
            "s;Ecco;Not what I was going for here, buddy.|{c:e;Ecco;CloseEyes}Man, what do you take me for?{c:e;Ecco;NormalBlink} Some gold digger?",
            "s;Joshua;Not necessarily.",
            "s;Ecco;Anyway, I hear you're an arena fighter.",
            "e;Joshua;Smile",
            "s;Joshua;Yeah, I got the idea from my dad.|He would supplement arena fights with his mercenary work.",
            "e;Ecco;Smile",
            "s;Ecco;Smart man.|Anyway, I was wondering if you could get me in. I need a recommendation.",
            "e;Joshua;CloseEyes,NoSmile",
            "s;Joshua;I don't know about this.|{c:e;Joshua;NormalBlink}Arena fights can be rough. You never know who you'll be up against.|You'll probably be fine against an armored opponent or someone who can use dark magic,|but you can't guarantee you'll be up against someone like that every time.",
            "e;Ecco;CloseEyes,Smile",
            "s;Ecco;Please, I can handle myself.{c:e;Ecco;NormalBlink,Smile} I'm a big girl.",
            "s;Joshua;Really? You look small and slender to me.",
            "s;Ecco;Tell you what. We spar, and if I win, you need to get me into the arena.",
            "e;Joshua;Smile",
            "s;Joshua;Sure, let's go.",
            "unlock_support_rank;Ecco;Joshua;C",
            "# Original script by Berserker Sam #",
            "elif;support_rank_nid == 'S'",
            "unlock_support_rank;Ecco;Joshua;S",
            "disable_support_rank;Joshua;Krista;S",
            "disable_support_rank;Joshua;Chell;S",
            "disable_support_rank;Alex;Joshua;S",
            "disable_support_rank;Ecco;Anil;S",
            "disable_support_rank;Joshua;Yumi;S",
            "end",
            "mf",
            "t;close",
            "b",
            "t;open"
        ],
        "nid": "Global SupportEccoJoshua"
    }
]