[
    {
        "name": "SupportKristaParker",
        "trigger": "on_support",
        "level_nid": null,
        "condition": "check_pair('Krista', 'Parker')",
        "commands": [],
        "only_once": false,
        "priority": 20,
        "_source": [
            "t;close",
            "if;support_rank_nid == 'C'",
            "b;CastleInterior",
            "t;open",
            "m;Girl of the Plains",
            "uu;Parker;Left;Krista;Right",
            "e;Parker;Smile",
            "s;Parker;Ah, Krista. Would you like to play a round or two of chess?|It's been a while since we last played.",
            "e;Krista;Smile",
            "s;Krista;Sure!{c:e;Krista;CloseEyes,Smile} And I'm gonna win this time.|I'm wayyy smarter than I was years ago.|{c:e;Krista;NormalBlink,Smile}I've got totally flawless strategies up my sleeve.",
            "e;Parker;CloseEyes,Smile",
            "s;Parker;We'll see about that.",
            "rrr",
            "t;close",
            "b;Library",
            "t;open",
            "uu;Krista;Right;Parker;Left",
            "e;Krista;HalfCloseEyes",
            "s;Krista;Okay, so we've got a bunch of pawns here, a bunch of pawns there,|both of us still got our queens, but he's down a knight, so...;;;thought_bubble",
            "s;Krista;Hmmmmmm{tgm}...",
            "e;Parker;HalfCloseEyes,Smile",
            "s;Parker;So, about those \"flawless strategies\"{tgm}...",
            "e;Krista;NormalBlink",
            "s;Krista;Shh! I'm focused. So focused.",
            "e;Parker;CloseEyes,Smile",
            "s;Parker;Practically locked onto the board.",
            "e;Krista;Smile",
            "s;Krista;Yup!",
            "e;Parker;HalfCloseEyes,Smile",
            "s;Parker;So locked on that you haven't made your move yet.",
            "e;Krista;NoSmile",
            "s;Krista;Give me a second! {tgm}{c:e;Krista;HalfCloseEyes}...",
            "e;Krista;NormalBlink",
            "bop;Krista",
            "e;Krista;Smile",
            "s;Krista;There. Perfect position for my bishop.",
            "e;Parker;NormalBlink,Smile",
            "s;Parker;Are you sure about that?",
            "e;Krista;NoSmile",
            "s;Krista;What are you--|{c:e;Krista;HalfCloseEyes}Nooooo, you gotta be kidding me{tgm}...!",
            "e;Parker;CloseEyes,Smile",
            "s;Parker;So, you see it too.|{c:e;Parker;NormalBlink,Smile}I'll go ahead with the move we're both seeing, then.",
            "bop;Parker",
            "e;Parker;CloseEyes,Smile",
            "s;Parker;There goes that bishop.",
            "e;Krista;CloseEyes",
            "s;Krista;Fine, whatever. It's just one bishop.|{c:e;Krista;NormalBlink}I can totally bounce back from this!",
            "e;Parker;HalfCloseEyes,Smile",
            "s;Parker;With your \"flawless strategy\"?",
            "e;Krista;CloseEyes,Smile",
            "s;Krista;You get it!",
            "rrr",
            "t;close",
            "b;BlackBackground",
            "t;open",
            "s;;Several moves later...;;125;hint;NumLines=1;no_sound",
            "t;close",
            "b;Library",
            "t;open",
            "uu;Krista;Right;Parker;Left",
            "e;Parker;CloseEyes,Smile",
            "s;Parker;And that's checkmate.",
            "e;Krista;CloseEyes",
            "s;Krista;Man{tgm}...",
            "e;Parker;NormalBlink,Smile",
            "s;Parker;Good game, Krista.|Your move-by-move analysis of the board has improved since our last game years ago.",
            "e;Krista;NormalBlink",
            "s;Krista;Really?",
            "e;Parker;CloseEyes,Smile",
            "s;Parker;Mm-hm.|{c:e;Parker;NormalBlink,Smile}At any rate, I have important business to attend to, so we'll leave it at that.|See you later, Krista. Don't cause too much trouble out there.",
            "unlock_support_rank;Parker;Krista;C",
            "elif;support_rank_nid == 'S'",
            "unlock_support_rank;Krista;Felicity;S",
            "disable_support_rank;Krista;Forrest;S",
            "disable_support_rank;Krista;Kai;S",
            "disable_support_rank;Krista;Trevor;S",
            "disable_support_rank;Krista;Sam;S",
            "disable_support_rank;Krista;Felicity;S",
            "disable_support_rank;Krista;Joshua;S",
            "disable_support_rank;Krista;Khalid;A+",
            "disable_support_rank;Krista;Masashi;A+",
            "disable_support_rank;Krista;Hikaru;S",
            "disable_support_rank;Krista;Matthew;S",
            "disable_support_rank;Parker;Cole;A+",
            "disable_support_rank;Parker;Shula;S",
            "end",
            "mf",
            "t;close",
            "b",
            "t;open"
        ],
        "nid": "Global SupportKristaParker"
    }
]