[
    {
        "nid": "KIRAZ",
        "name": "Wild Magic",
        "desc": "Grants +5 to any <red>major stat</> or +10 to Hit, Avo, or Crit at the start of each turn.",
        "icon_nid": "Skills",
        "icon_index": [
            9,
            40
        ],
        "components": [
            [
                "class_skill",
                null
            ],
            [
                "stat_change_expression",
                [
                    [
                        "MAG",
                        "5 if v('kirazSkill') == 0 else 0"
                    ],
                    [
                        "SKL",
                        "5 if v('kirazSkill') == 1 else 0"
                    ],
                    [
                        "SPD",
                        "5 if v('kirazSkill') == 2 else 0"
                    ],
                    [
                        "LCK",
                        "5 if v('kirazSkill') == 3 else 0"
                    ],
                    [
                        "DEF",
                        "5 if v('kirazSkill') == 4 else 0"
                    ],
                    [
                        "RES",
                        "5 if v('kirazSkill') == 5 else 0"
                    ]
                ]
            ],
            [
                "eval_hit",
                "10 if v('kirazSkill') == 6 else 0"
            ],
            [
                "eval_avoid",
                "10 if v('kirazSkill') == 7 else 0"
            ],
            [
                "eval_crit",
                "10 if v('kirazSkill') == 8 else 0"
            ],
            [
                "multi_desc_lore",
                [
                    "MajorStats"
                ]
            ]
        ]
    }
]